smtp_mailer_nerdler/__init__.py
smtp_mailer_nerdler/smtp_mailer.py
smtp_mailer_nerdler-0.0.2.dist-info/METADATA
smtp_mailer_nerdler-0.0.2.dist-info/WHEEL
smtp_mailer_nerdler-0.0.2.dist-info/top_level.txt
smtp_mailer_nerdler-0.0.2.dist-info/RECORD
