Metadata-Version: 2.1
Name: smtp-mailer-nerdler
Version: 0.0.2
Summary: SMTP Mailer classes
Home-page: https://github.com/nerdlertech/smtp_mailer
Author: Nerdler
Author-email: pip@nerdler.tech
License: UNKNOWN
Project-URL: Bug Tracker, https://github.com/nerdlertech/smtp_mailer/issues
Platform: UNKNOWN
Classifier: Programming Language :: Python :: 3
Classifier: License :: OSI Approved :: MIT License
Classifier: Operating System :: OS Independent
Requires-Python: >=3.9
